trainer/__init__.py
trainer/_trainer.py
trainer/loaders.py
trainer/models.py
trainer/trainer.py
trainer/utils.py
cls_trainer_pytorch-0.0.1.dist-info/METADATA
cls_trainer_pytorch-0.0.1.dist-info/WHEEL
cls_trainer_pytorch-0.0.1.dist-info/top_level.txt
cls_trainer_pytorch-0.0.1.dist-info/RECORD
